{
    "version": "0.3.160",
    "description": "Command line deployment/management client for fly.io services",
    "homepage": "https://github.com/superfly/flyctl",
    "license": " Apache-2.0",
    "architecture": {
        "64bit": {
            "url": "https://github.com/superfly/flyctl/releases/download/v0.3.160/flyctl_0.3.160_Windows_x86_64.zip",
            "hash": "cf2504ac221ae8057ebdb3ee17813edfdefb6c7d5a20a8ae0cd9141e2b59c38c"
        }
    },
    "bin": [
        "flyctl.exe",
        [
            "flyctl.exe",
            "fly"
        ]
    ],
    "checkver": "github",
    "autoupdate": {
        "architecture": {
            "64bit": {
                "url": "https://github.com/superfly/flyctl/releases/download/v$version/flyctl_$version_Windows_x86_64.zip"
            }
        }
    }
}
