{
    "version": "0.3.163",
    "description": "Command line deployment/management client for fly.io services",
    "homepage": "https://github.com/superfly/flyctl",
    "license": " Apache-2.0",
    "architecture": {
        "64bit": {
            "url": "https://github.com/superfly/flyctl/releases/download/v0.3.163/flyctl_0.3.163_Windows_x86_64.zip",
            "hash": "97f6e49c2f2a2cfb848a87685da334f61d9bc5c4cd4a823e9b499aa303ffcd50"
        }
    },
    "bin": [
        "flyctl.exe",
        [
            "flyctl.exe",
            "fly"
        ]
    ],
    "checkver": "github",
    "autoupdate": {
        "architecture": {
            "64bit": {
                "url": "https://github.com/superfly/flyctl/releases/download/v$version/flyctl_$version_Windows_x86_64.zip"
            }
        }
    }
}
