{
    "version": "1.29.2",
    "description": "An open platform-independent service mesh that provides traffic management, policy enforcement, and telemetry collection.",
    "homepage": "https://istio.io",
    "license": "Apache-2.0",
    "architecture": {
        "64bit": {
            "url": "https://github.com/istio/istio/releases/download/1.29.2/istio-1.29.2-win.zip",
            "hash": "58d8a6659ee1ef1fb11008a6ec436a4fe2365ffe2d1f11645136cbe0ed4e22c3"
        }
    },
    "extract_dir": "istio-1.29.2",
    "bin": "bin\\istioctl.exe",
    "checkver": {
        "github": "https://github.com/istio/istio"
    },
    "autoupdate": {
        "architecture": {
            "64bit": {
                "url": "https://github.com/istio/istio/releases/download/$version/istio-$version-win.zip"
            }
        },
        "hash": {
            "url": "$url.sha256"
        },
        "extract_dir": "istio-$version"
    }
}
