{
    "version": "1.26.0",
    "description": "A command line interface to push/pull workspaces to/from the Structurizr cloud service/on-premises installation, and export views to PlantUML, Mermaid, and WebSequenceDiagrams formats.",
    "homepage": "https://github.com/structurizr/cli",
    "license": "Apache-2.0",
    "suggest": {
        "java": "java/oraclejre8"
    },
    "url": "https://github.com/structurizr/cli/releases/download/v1.26.0/structurizr-cli-1.26.0.zip",
    "hash": "4fb1968b5dd812d90b3e66611a991dbb76d623c6c43e51b2ce381257079cff5a",
    "bin": "structurizr.bat",
    "checkver": "github",
    "autoupdate": {
        "url": "https://github.com/structurizr/cli/releases/download/v$version/structurizr-cli-$version.zip"
    }
}
