{
    "version": "20230308",
    "description": "Split screen video comparison tool using FFmpeg and SDL2.",
    "homepage": "https://github.com/pixop/video-compare",
    "license": "GPL-2.0-only",
    "architecture": {
        "64bit": {
            "url": "https://github.com/pixop/video-compare/releases/download/20230308/video-compare-20230308-win10-x86_64.zip",
            "hash": "d5bd7c344b4d7f8a16752eb111b6b65a74bbbb0d64e5d2ad1e4a9e08c34a8fee"
        }
    },
    "bin": "video-compare.exe",
    "checkver": "github",
    "autoupdate": {
        "architecture": {
            "64bit": {
                "url": "https://github.com/pixop/video-compare/releases/download/$version/video-compare-$version-win10-x86_64.zip"
            }
        }
    }
}
